qoqo_aqt-0.8.0.dist-info/METADATA
qoqo_aqt-0.8.0.dist-info/WHEEL
qoqo_aqt-0.8.0.dist-info/licenses/LICENSE
qoqo_aqt/OPENSSL_LICENSE
qoqo_aqt/DEPENDENCIES
qoqo_aqt/__init__.py
qoqo_aqt/PYTHON_LICENSE
qoqo_aqt/LICENSE_FOR_BINARY_DISTRIBUTION
qoqo_aqt/qoqo_aqt.cpython-39-darwin.so
qoqo_aqt-0.8.0.dist-info/RECORD
