Metadata-Version: 2.3
Name: qoqo_aqt
Version: 0.8.0
Requires-Dist: numpy
Requires-Dist: qoqo-calculator-pyo3 >=1.2, <1.3
Requires-Dist: qoqo >=1.13, <1.14
Requires-Dist: sphinx >=2.1 ; extra == 'docs'
Requires-Dist: nbsphinx ; extra == 'docs'
Requires-Dist: pygments ; extra == 'docs'
Requires-Dist: recommonmark ; extra == 'docs'
Requires-Dist: myst-parser ; extra == 'docs'
Requires-Dist: sphinx-rtd-theme ; extra == 'docs'
Requires-Dist: tomli ; extra == 'docs'
Provides-Extra: docs
License-File: LICENSE
Summary: AQT backend for qoqo quantum computing toolkit
Home-Page: https://github.com/HQSquantumsimulations/qoqo_aqt
Author: HQS Quantum Simulations <info@quantumsimulations.de>
Author-email: HQS Quantum Simulations <info@quantumsimulations.de>
Maintainer-email: HQS Quantum Simulations GmbH <info@quantumsimulations.de>
License: Apache-2.0 AND Apache-2.0 with LLVM-exception AND MIT AND Unicode-DFS-2016 AND
Requires-Python: >=3.7
Project-URL: Source Code, https://github.com/HQSquantumsimulations/qoqo_aqt
